sfm_utils/VERSION
sfm_utils/__init__.py
sfm_utils/parse.py
sfm_utils/sfm_sniffer.py
sfm_utils/tag_analyser.py
sfm_utils/tag_value_collection.py
sfm_utils/type_deductor.py
sfm_utils-0.1.0rc1.post1.dist-info/METADATA
sfm_utils-0.1.0rc1.post1.dist-info/RECORD
sfm_utils-0.1.0rc1.post1.dist-info/WHEEL
sfm_utils-0.1.0rc1.post1.dist-info/entry_points.txt
sfm_utils-0.1.0rc1.post1.dist-info/top_level.txt
