Metadata-Version: 2.1
Name: sfm-utils
Version: 0.1.0rc1.post1
Summary: utilities for working with lexicography data encoded using Standard Format Markers (SFM data files).
Home-page: https://gitlab.com/bbsg/sfm_utils
Author: Gavin Falconer
Author-email: gfalconer@expressivelogic.co.uk
License: MIT
Keywords: SFM MDF SIL lexicon lexicography expressivelogic
Platform: UNKNOWN
Classifier: Development Status :: 2 - Pre-Alpha
Classifier: License :: OSI Approved :: MIT License
Classifier: Programming Language :: Python :: 3 :: Only
Classifier: Intended Audience :: Science/Research
Classifier: Topic :: Text Processing :: Linguistic
Classifier: Operating System :: OS Independent
Classifier: Environment :: Console
Requires-Python: >=3
Requires-Dist: docopt
Requires-Dist: six
